tkitreadability/__init__.py
tkitreadability/tkitreadability.py
tkitreadability-0.0.0.5.3.dist-info/LICENSE
tkitreadability-0.0.0.5.3.dist-info/METADATA
tkitreadability-0.0.0.5.3.dist-info/WHEEL
tkitreadability-0.0.0.5.3.dist-info/top_level.txt
tkitreadability-0.0.0.5.3.dist-info/RECORD
