Metadata-Version: 2.1
Name: tkitreadability
Version: 0.0.0.5.3
Summary: Terry toolkit tkitreadability
Home-page: https://docs.terrychan.org/tkitreadability/
Author: Terry Chan
Author-email: napoler2008@gmail.com
License: UNKNOWN
Platform: UNKNOWN
License-File: LICENSE
Requires-Dist: html2text (==2020.1.16)
Requires-Dist: readability-lxml (==0.8.1)
Requires-Dist: Markdown (==3.4.1)
